README.md
allenact_plugins/__init__.py
allenact_plugins/setup.py
allenact_plugins.egg-info/PKG-INFO
allenact_plugins.egg-info/SOURCES.txt
allenact_plugins.egg-info/dependency_links.txt
allenact_plugins.egg-info/requires.txt
allenact_plugins.egg-info/top_level.txt
allenact_plugins/babyai_plugin/__init__.py
allenact_plugins/babyai_plugin/babyai_constants.py
allenact_plugins/babyai_plugin/babyai_models.py
allenact_plugins/babyai_plugin/babyai_tasks.py
allenact_plugins/babyai_plugin/configs/__init__.py
allenact_plugins/babyai_plugin/data/__init__.py
allenact_plugins/babyai_plugin/scripts/__init__.py
allenact_plugins/babyai_plugin/scripts/download_babyai_expert_demos.py
allenact_plugins/babyai_plugin/scripts/get_instr_length_percentiles.py
allenact_plugins/babyai_plugin/scripts/truncate_expert_demos.py
allenact_plugins/clip_plugin/__init__.py
allenact_plugins/clip_plugin/clip_preprocessors.py
allenact_plugins/gym_plugin/__init__.py
allenact_plugins/gym_plugin/gym_distributions.py
allenact_plugins/gym_plugin/gym_environment.py
allenact_plugins/gym_plugin/gym_models.py
allenact_plugins/gym_plugin/gym_sensors.py
allenact_plugins/gym_plugin/gym_tasks.py
allenact_plugins/habitat_plugin/__init__.py
allenact_plugins/habitat_plugin/habitat_constants.py
allenact_plugins/habitat_plugin/habitat_environment.py
allenact_plugins/habitat_plugin/habitat_preprocessors.py
allenact_plugins/habitat_plugin/habitat_sensors.py
allenact_plugins/habitat_plugin/habitat_task_samplers.py
allenact_plugins/habitat_plugin/habitat_tasks.py
allenact_plugins/habitat_plugin/habitat_utils.py
allenact_plugins/habitat_plugin/data/__init__.py
allenact_plugins/habitat_plugin/scripts/__init__.py
allenact_plugins/habitat_plugin/scripts/agent_demo.py
allenact_plugins/habitat_plugin/scripts/make_map.py
allenact_plugins/ithor_plugin/__init__.py
allenact_plugins/ithor_plugin/ithor_constants.py
allenact_plugins/ithor_plugin/ithor_environment.py
allenact_plugins/ithor_plugin/ithor_sensors.py
allenact_plugins/ithor_plugin/ithor_task_samplers.py
allenact_plugins/ithor_plugin/ithor_tasks.py
allenact_plugins/ithor_plugin/ithor_util.py
allenact_plugins/ithor_plugin/ithor_viz.py
